{
    "Recommend a hotel with great family-friendly amenities.": 0.6774193548387096,
    "Recommend a hotel with the best poolside service.": 0.8333333333333334,
    "Suggest a hotel with a magical ambiance.": 0.5625,
    "Where can I find a hotel that balances luxury and affordability?": 0.3157894736842105,
    "Suggest a hotel with the best spa services.": 0.5,
    "Where can I stay near the best art museums?": 0.3888888888888889,
    "Recommend a hotel with a lively atmosphere.": 0.5428571428571428,
    "Where can I find hotels that combine adventure and relaxation?": 1.0,
    "What are some of the best hotels for gourmet lovers?": 0.5,
    "Suggest a hotel with excellent fine dining.": 0.3181818181818182,
    "Where can I stay that feels youthful and energetic?": 0.4594594594594595,
    "I want a hotel that makes me feel like I\u2019m in a movie.": 0.46875,
    "Where can I stay to fully experience the nightlife of a city?": 0.44642857142857145,
    "Where can I stay to get the best of both city and nature?": 0.5217391304347826,
    "What are the top boutique hotels?": 0.34545454545454546,
    "Recommend a pet-friendly hotel.": 0.4482758620689655,
    "Where can I find hotels with great rooftop bars?": 0.6956521739130435,
    "Recommend a hotel that keeps surprising me every day.": 0.5625,
    "Suggest a hotel where I can just go with the flow.": 0.2727272727272727,
    "What are the best hotels for exploring hidden gems in a city?": 0.5,
    "Where can I stay with beautiful waterfront views?": 0.7692307692307693,
    "Where can I find hotels with a unique architectural design?": 0.4375,
    "Looking for a hotel with creative spaces and an artsy vibe.": 0.5416666666666666,
    "What are the best hotels for wellness and relaxation?": 0.4444444444444444,
    "What are the top hotels for a scenic retreat?": 0.4444444444444444,
    "Which hotels offer the best opportunities for socializing?": 0.7142857142857143,
    "Recommend a hotel for travellers who just want to people-watch.": 0.375,
    "Recommend a hotel that feels intimate and private.": 0.24390243902439024,
    "Recommend a hotel that matches a slower travel rhythm.": 0.5714285714285714,
    "Recommend a hotel that works well for group celebrations.": 0.6666666666666666,
    "Recommend a hotel that works well for traveling with teenagers.": 0.43478260869565216,
    "Recommend a hotel with a nostalgic, vintage vibe.": 0.25,
    "Recommend a place for a solo birthday trip.": 0.36,
    "Recommend a place where I won't feel like a tourist.": 0.32608695652173914,
    "Suggest a hotel that complements a journaling or reflection-focused trip.": 0.7142857142857143,
    "Suggest a hotel that doesn't feel too polished.": 0.2692307692307692,
    "Suggest a hotel that works well for working remotely.": 0.4444444444444444,
    "Suggest a hotel that's perfect for art lovers.": 0.8571428571428571,
    "What are some hotels that are great for slow mornings?": 1.0,
    "What hotels are affordable but don't feel basic?": 0.32786885245901637,
    "Where can I stay for the best sunrise or sunset views?": 0.5555555555555556,
    "Where can I stay if I'm traveling with elderly parents?": 0.5333333333333333,
    "Where can I stay that fits a minimalist travel style?": 0.6666666666666666,
    "Where can I stay that fits well with a photography-heavy trip?": 0.8,
    "Where can I stay that works for multiple generations?": 0.5084745762711864,
    "Where can I stay that works well with young kids and no fuss?": 0.5333333333333333,
    "Where can I stay to avoid the tourist rush without going remote?": 0.2857142857142857,
    "Where should I stay during a creative block?": 0.6666666666666666,
    "Where should I stay for easy airport access?": 0.625,
    "Where should I stay that matches a high-energy trip?": 0.5
}